cloudssh/__init__.py
cloudssh/__main__.py
cloudssh/cloudssh.py
cloudssh-1.4.dist-info/LICENSE
cloudssh-1.4.dist-info/METADATA
cloudssh-1.4.dist-info/WHEEL
cloudssh-1.4.dist-info/entry_points.txt
cloudssh-1.4.dist-info/top_level.txt
cloudssh-1.4.dist-info/RECORD
