Metadata-Version: 2.1
Name: cloudssh
Version: 1.4
Summary: EC2 SSH connections helper
Home-page: https://github.com/gabfl/cloudssh
Author: gab
Author-email: gab@confiant.com
License: UNKNOWN
Platform: UNKNOWN
Classifier: Topic :: Software Development
Classifier: License :: OSI Approved :: MIT License
Classifier: Operating System :: POSIX :: Linux
Classifier: Natural Language :: English
Classifier: Programming Language :: Python :: 3
Classifier: Programming Language :: Python
Classifier: Development Status :: 4 - Beta
Requires-Dist: argparse
Requires-Dist: boto3
